{"errors":[],"warnings":[],"namedChunkGroups":{"polyfill":{"chunks":[0,7],"assets":["webpack-runtime-6732d582bacc44a35ac1.js","webpack-runtime-6732d582bacc44a35ac1.js.map","polyfill-d838bf258599ed4db329.js","polyfill-d838bf258599ed4db329.js.map"],"children":{},"childAssets":{}},"app":{"chunks":[0,6,3],"assets":["webpack-runtime-6732d582bacc44a35ac1.js","webpack-runtime-6732d582bacc44a35ac1.js.map","framework-d066f55745d479a55fde.js","framework-d066f55745d479a55fde.js.map","app-c38a6cd7bfd2231c1db6.js","app-c38a6cd7bfd2231c1db6.js.map"],"children":{},"childAssets":{}},"component---src-pages-index-tsx":{"chunks":[8,4,2,1,5],"assets":["styles.1957cd5675d8a73816b6.css","styles-8fab2804fb6f85b824b6.js","styles-8fab2804fb6f85b824b6.js.map","cfcfc25b-57a88139069894bbad31.js","cfcfc25b-57a88139069894bbad31.js.map","9954539a-e55798e0a2846c452d2a.js","9954539a-e55798e0a2846c452d2a.js.map","87c96e3e-c8fc4603c7e0245d038a.js","87c96e3e-c8fc4603c7e0245d038a.js.map","component---src-pages-index-tsx-210363a80b73e2f628bc.js","component---src-pages-index-tsx-210363a80b73e2f628bc.js.map"],"children":{},"childAssets":{}}},"assetsByChunkName":{"polyfill":["webpack-runtime-6732d582bacc44a35ac1.js","polyfill-d838bf258599ed4db329.js"],"app":["webpack-runtime-6732d582bacc44a35ac1.js","framework-d066f55745d479a55fde.js","app-c38a6cd7bfd2231c1db6.js"],"component---src-pages-index-tsx":["styles.1957cd5675d8a73816b6.css","styles-8fab2804fb6f85b824b6.js","cfcfc25b-57a88139069894bbad31.js","9954539a-e55798e0a2846c452d2a.js","87c96e3e-c8fc4603c7e0245d038a.js","component---src-pages-index-tsx-210363a80b73e2f628bc.js"]}}